python_project_raphael_corchia/__init__.py
python_project_raphael_corchia/blockchain/backtest.pkl
python_project_raphael_corchia/python_project.py
python_project_raphael_corchia-0.2.7.dist-info/LICENSE
python_project_raphael_corchia-0.2.7.dist-info/METADATA
python_project_raphael_corchia-0.2.7.dist-info/WHEEL
python_project_raphael_corchia-0.2.7.dist-info/RECORD
