Metadata-Version: 2.3
Name: python_project_raphael_corchia
Version: 0.2.7
Summary: Add feature to pybacktestchain
License: MIT
Author: Raphael Corchia
Requires-Python: >=3.10,<3.13
Classifier: License :: OSI Approved :: MIT License
Classifier: Programming Language :: Python :: 3
Classifier: Programming Language :: Python :: 3.10
Classifier: Programming Language :: Python :: 3.11
Classifier: Programming Language :: Python :: 3.12
Requires-Dist: gitdb (==4.0.10)
Requires-Dist: gitpython (>=3.1.44,<4.0.0)
Requires-Dist: numba (>=0.60.0,<0.61.0)
Requires-Dist: plotly (>=5.24.1,<6.0.0)
Requires-Dist: pybacktestchain (>=0.2.1,<0.3.0)
Requires-Dist: scipy (>=1.11,<1.14)
Requires-Dist: streamlit (>=1.41.1,<2.0.0)
